[
    {
        "Numero": 1,
        "Nome": "Gol",
        "Tipo": "Hatch",
        "Marca": "Volkswagen",
        "Imagem": "\\img\\Volkswagen\\Gol.jpg"
    },
    {
        "Numero": 2,
        "Nome": "Nivus",
        "Tipo": "SUV",
        "Marca": "Volkswagen",
        "Imagem": "\\img\\Volkswagen\\Nivus.jpg"
    },
    {
        "Numero": 3,
        "Nome": "Polo",
        "Tipo": "Hatch",
        "Marca": "Volkswagen",
        "Imagem": "\\img\\Volkswagen\\Polo.jpg"
    },
    {
        "Numero": 4,
        "Nome": "Tiguan",
        "Tipo": "SUV",
        "Marca": "Volkswagen",
        "Imagem": "\\img\\Volkswagen\\Tiguan.jpg"
    },

        {
            "Numero": 5,
            "Nome": "Astra-SS",
            "Tipo": "Sedan",
            "Marca": "Chevrolet",
            "Imagem": "\\img\\Chevrolet\\Astra-SS.jpeg"
            
        },
        {
            "Numero": 6,
            "Nome": "Corvete-C8",
            "Tipo": "Cupê",
            "Marca": "Chevrolet",
            "Imagem": "\\img\\Chevrolet\\Corvette-C8.jpg"
        },
        {
            "Numero": 7,
            "Nome": "Cruze",
            "Tipo": "Hatch",
            "Marca": "Chevrolet",
            "Imagem": "\\img\\Chevrolet\\Cruze.jpg"
        },
        {
            "Numero": 8,
            "Nome": "Tracker-Rs",
            "Tipo": "SUV",
            "Marca": "Chevrolet",
            "Imagem": "\\img\\Chevrolet\\Tracker-RS.jpg"
        },

    {
        "Numero": 9,
        "Nome": "320i-M",
        "Tipo": "Cupê",
        "Marca": "Bmw",
        "Imagem": "\\img\\Bmw\\320I-M.jpg"
    },
    {
        "Numero": 10,
        "Nome": "M2",
        "Tipo": "Cupê",
        "Marca": "Bmw",
        "Imagem": "\\img\\Bmw\\M2.jpeg"
    },

    {
        "Numero": 11,
        "Nome": "X6-M",
        "Tipo": "SUV-Cupê",
        "Marca": "Bmw",
        "Imagem": "\\img\\Bmw\\X6M.jpg"
    },

    {
        "Numero": 12,
        "Nome": "X1",
        "Tipo": "SUV",
        "Marca": "Bmw",
        "Imagem": "\\img\\Bmw\\X1.jpg"
    },

        {
            "Numero": 13,
            "Nome": "Hb20 - Hatch",
            "Tipo": "SUV",
            "Marca": "Hyundai",
            "Imagem": "\\img\\Hyundai\\Hb20-Hatch.jpg"
        },
        {
            "Numero": 14,
            "Nome": "Hb20 - RSpec",
            "Tipo": "SUV",
            "Marca": "Hyundai",
            "Imagem": "\\img\\Hyundai\\Hb20-RSpec.jpg"
        },
        {
            "Numero": 15,
            "Nome": "I30",
            "Tipo": "SUV",
            "Marca": "Hyundai",
            "Imagem": "\\img\\Hyundai\\I30.jpg"
        },
        {
            "Numero":16,
            "Nome": "Sonata",
            "Tipo": "SUV",
            "Marca": "Hyundai",
            "Imagem": "\\img\\Hyundai\\Sonata.jpg"
        }

]
